ixian_docker/__init__.py
ixian_docker/modules/__init__.py
ixian_docker/modules/black/__init__.py
ixian_docker/modules/black/config.py
ixian_docker/modules/black/tasks.py
ixian_docker/modules/bower/README.md
ixian_docker/modules/bower/__init__.py
ixian_docker/modules/bower/config.py
ixian_docker/modules/bower/tasks.py
ixian_docker/modules/django/Dockerfile.template
ixian_docker/modules/django/__init__.py
ixian_docker/modules/django/config.py
ixian_docker/modules/django/tasks.py
ixian_docker/modules/docker/Dockerfile.template
ixian_docker/modules/docker/README.md
ixian_docker/modules/docker/__init__.py
ixian_docker/modules/docker/checker.py
ixian_docker/modules/docker/config.py
ixian_docker/modules/docker/tasks.py
ixian_docker/modules/docker/utils/__init__.py
ixian_docker/modules/docker/utils/builder.py
ixian_docker/modules/docker/utils/client.py
ixian_docker/modules/docker/utils/compose.py
ixian_docker/modules/docker/utils/dockerfile.py
ixian_docker/modules/docker/utils/images.py
ixian_docker/modules/docker/utils/print.py
ixian_docker/modules/docker/utils/volumes.py
ixian_docker/modules/eslint/__init__.py
ixian_docker/modules/eslint/config.py
ixian_docker/modules/eslint/tasks.py
ixian_docker/modules/jest/__init__.py
ixian_docker/modules/jest/config.py
ixian_docker/modules/jest/tasks.py
ixian_docker/modules/npm/__init__.py
ixian_docker/modules/npm/config.py
ixian_docker/modules/npm/tasks.py
ixian_docker/modules/npm/utils.py
ixian_docker/modules/prettier/__init__.py
ixian_docker/modules/prettier/config.py
ixian_docker/modules/prettier/tasks.py
ixian_docker/modules/pytest/__init__.py
ixian_docker/modules/pytest/config.py
ixian_docker/modules/pytest/tasks.py
ixian_docker/modules/python/__init__.py
ixian_docker/modules/python/config.py
ixian_docker/modules/python/tasks.py
ixian_docker/modules/python2/Dockerfile.template
ixian_docker/modules/python2/__init__.py
ixian_docker/modules/python2/config.py
ixian_docker/modules/python2/tasks.py
ixian_docker-0.1.0.dev5.dist-info/LICENSE-2.0.txt
ixian_docker-0.1.0.dev5.dist-info/METADATA
ixian_docker-0.1.0.dev5.dist-info/NOTICE
ixian_docker-0.1.0.dev5.dist-info/WHEEL
ixian_docker-0.1.0.dev5.dist-info/pbr.json
ixian_docker-0.1.0.dev5.dist-info/top_level.txt
ixian_docker-0.1.0.dev5.dist-info/RECORD
