Metadata-Version: 2.1
Name: ixian-docker
Version: 0.1.0.dev5
Summary: Ixian modules for Docker support.
Home-page: https://github.com/kreneskyp/ixian-docker
Author: Peter Krenesky
Author-email: kreneskyp@gmail.com
Maintainer: Peter Krenesky
Maintainer-email: kreneskyp@gmail.com
License: Apache License, Version 2.0
Keywords: tasks, shovel, rake, make, ixian, ix, docker
Platform: UNKNOWN
Classifier: License :: OSI Approved :: Apache Software License
Classifier: Intended Audience :: Developers
Classifier: Intended Audience :: System Administrators
Classifier: Programming Language :: Python
Classifier: Programming Language :: Python :: 3
Classifier: Programming Language :: Python :: 3.6
Classifier: Programming Language :: Python :: 3.7
Classifier: Programming Language :: Python :: 3.8
Classifier: Development Status :: 3 - Alpha
Classifier: Operating System :: OS Independent
Classifier: Topic :: Software Development :: Build Tools
Requires-Dist: argcomplete (==1.9.4)
Requires-Dist: argparse (==1.4.0)
Requires-Dist: docker (==4.1.0)
Requires-Dist: jinja2 (==2.10.3)
Requires-Dist: ixian (==0.0.1.dev194)
Requires-Dist: boto3
